README.md
setup.py
contrib/__init__.py
contrib/app/__init__.py
contrib/app/terminal/__init__.py
contrib/app/web/__init__.py
contrib/data/__init__.py
contrib/data/ptb.py
contrib/eval/__init__.py
contrib/models/__init__.py
contrib/train/__init__.py
contrib/train/basic.py
contrib/train/generator.py
contrib/train/log.py
contrib/train/words.py
samples/__init__.py
test/__init__.py
test/test.py
tf_enhance.egg-info/PKG-INFO
tf_enhance.egg-info/SOURCES.txt
tf_enhance.egg-info/dependency_links.txt
tf_enhance.egg-info/requires.txt
tf_enhance.egg-info/top_level.txt
tfenhance/train/__init__.py