Metadata-Version: 2.1
Name: tf-enhance
Version: 0.0.5
Summary: An easy enhancement framework for TensorFlow.
Home-page: https://github.com/LovelyLazyCat/tf-enhance
Author: LazyCat
Author-email: lazycat7703@gmail.com
License: UNKNOWN
Platform: UNKNOWN
Classifier: Development Status :: 3 - Alpha
Classifier: Programming Language :: Python :: 3.6
